randomCoordinates
