Metadata-Version: 2.1
Name: randomCoordinates
Version: 0.1.7
Summary: A very basic Random Coordinates Generator
Home-page: UNKNOWN
Author: scruffysnake
Author-email: scruffysnake@scruffysnake.com
License: MIT
Keywords: RNG
Platform: UNKNOWN
Classifier: Development Status :: 5 - Production/Stable
Classifier: Intended Audience :: Education
Classifier: Operating System :: Microsoft :: Windows :: Windows 10
Classifier: License :: OSI Approved :: MIT License
Classifier: Programming Language :: Python :: 3
License-File: LICENCE.txt
